fmpxx/__init__.py
fmpxx/base.py
fmpxx/exceptions.py
fmpxx/financials.py
fmpxx/stocks.py
fmpxx/utils.py
fmpxx-0.3.8.dist-info/METADATA
fmpxx-0.3.8.dist-info/WHEEL
fmpxx-0.3.8.dist-info/top_level.txt
fmpxx-0.3.8.dist-info/RECORD
