Metadata-Version: 2.4
Name: fmpxx
Version: 0.3.8
Summary: Add your description here
Requires-Python: >=3.11.11
Requires-Dist: pandas>=2.2.3
Requires-Dist: python-dotenv>=1.0.1
Requires-Dist: requests>=2.32.3
Requires-Dist: retry>=0.9.2
